{
  "socks5_proxy_host": "127.0.0.1",
  "socks5_proxy_port": 18001,
  "vps_out_ip": "185.226.95.85",
  "vps_out_control_port": 8888,
  "udp_listen_port": 10808,
  "socks5_listen_host": "127.0.0.1",
  "socks5_listen_port": 10808,
  "udp_mtu": 1200,
  "udp_recv_buffer_bytes": 4194304,
  "socket_buffer_bytes": 4194304,
  "client_recv_size": 65536,
  "log_file": "log_in_runtime.log",
  "log_level": "INFO",
  "log_max_bytes": 20971520,
  "log_backup_count": 5,
  "keepalive_interval": 3.0,
  "keepalive_timeout": 10.0,
  "control_timeout": 15.0,
  "socks5_connect_timeout": 10.0,
  "session_close_grace": 1.0
}
